omero_annotate_ai/__init__.py
omero_annotate_ai/core/__init__.py
omero_annotate_ai/core/annotation_config.py
omero_annotate_ai/core/annotation_pipeline.py
omero_annotate_ai/omero/__init__.py
omero_annotate_ai/omero/omero_functions.py
omero_annotate_ai/omero/omero_utils.py
omero_annotate_ai/omero/simple_connection.py
omero_annotate_ai/processing/__init__.py
omero_annotate_ai/processing/file_io_functions.py
omero_annotate_ai/processing/image_functions.py
omero_annotate_ai/processing/training_functions.py
omero_annotate_ai/processing/training_utils.py
omero_annotate_ai/processing/utils.py
omero_annotate_ai/utils/__init__.py
omero_annotate_ai/utils/logging.py
omero_annotate_ai/widgets/__init__.py
omero_annotate_ai/widgets/omero_connection_widget.py
omero_annotate_ai/widgets/training_data_widget.py
omero_annotate_ai/widgets/workflow_widget.py
omero_annotate_ai-0.1.2.dist-info/licenses/LICENSE
omero_annotate_ai-0.1.2.dist-info/METADATA
omero_annotate_ai-0.1.2.dist-info/WHEEL
omero_annotate_ai-0.1.2.dist-info/top_level.txt
omero_annotate_ai-0.1.2.dist-info/RECORD
