Metadata-Version: 2.4
Name: omero-annotate-ai
Version: 0.1.2
Summary: OMERO integration for AI-powered image annotation and segmentation workflows
Author-email: Maarten Paul <m.w.paul@lumc.nl>
Maintainer-email: Maarten Paul <m.w.paul@lumc.nl>
License: Apache License
Project-URL: Homepage, https://github.com/Leiden-Cell-Observatory/omero_annotate_ai
Project-URL: Repository, https://github.com/Leiden-Cell-Observatory/omero_annotate_ai.git
Project-URL: Issues, https://github.com/Leiden-Cell-Observatory/omero_annotate_ai/issues
Project-URL: Documentation, https://github.com/Leiden-Cell-Observatory/omero_annotate_ai#readme
Project-URL: Changelog, https://github.com/Leiden-Cell-Observatory/omero_annotate_ai/releases
Keywords: omero,microscopy,segmentation,ai,annotation,sam,micro-sam
Classifier: Development Status :: 3 - Alpha
Classifier: Intended Audience :: Science/Research
Classifier: License :: OSI Approved :: Apache Software License
Classifier: Operating System :: OS Independent
Classifier: Programming Language :: Python :: 3
Classifier: Programming Language :: Python :: 3.8
Classifier: Programming Language :: Python :: 3.9
Classifier: Programming Language :: Python :: 3.10
Classifier: Programming Language :: Python :: 3.11
Classifier: Programming Language :: Python :: 3.12
Classifier: Programming Language :: Python :: Implementation :: CPython
Classifier: Topic :: Scientific/Engineering :: Image Processing
Classifier: Topic :: Scientific/Engineering :: Bio-Informatics
Classifier: Topic :: Scientific/Engineering :: Artificial Intelligence
Classifier: Topic :: Scientific/Engineering :: Medical Science Apps.
Classifier: Environment :: Console
Classifier: Environment :: Other Environment
Requires-Python: >=3.8
License-File: LICENSE
Requires-Dist: numpy<2.0,>=1.21.0
Requires-Dist: pandas>=1.3.0
Requires-Dist: imageio>=2.9.0
Requires-Dist: zarr>=2.10.0
Requires-Dist: dask>=2021.6.0
Requires-Dist: pyyaml>=6.0
Requires-Dist: pydantic>=2.0.0
Requires-Dist: typing-extensions>=4.0.0
Requires-Dist: ipywidgets>=7.6.0
Requires-Dist: keyring>=23.0.0
Requires-Dist: ezomero>=3.1.0
Requires-Dist: ipykernel
Requires-Dist: pixi-kernel<0.7,>=0.6.6
Requires-Dist: opencv-python
Provides-Extra: microsam
Requires-Dist: napari>=0.4.15; extra == "microsam"
Provides-Extra: dev
Requires-Dist: pytest>=6.0; extra == "dev"
Requires-Dist: pytest-cov>=2.0; extra == "dev"
Requires-Dist: black>=22.0; extra == "dev"
Requires-Dist: isort>=5.0; extra == "dev"
Requires-Dist: flake8>=4.0; extra == "dev"
Provides-Extra: docs
Requires-Dist: mkdocs>=1.5.3; extra == "docs"
Requires-Dist: mkdocs-material>=9.5.9; extra == "docs"
Requires-Dist: mkdocstrings>=0.24.0; extra == "docs"
Requires-Dist: mkdocstrings-python>=1.7.0; extra == "docs"
Requires-Dist: mkdocs-gen-files>=0.5.0; extra == "docs"
Requires-Dist: mkdocs-literate-nav>=0.6.1; extra == "docs"
Requires-Dist: mkdocs-section-index>=0.3.8; extra == "docs"
Requires-Dist: mkdocs-autorefs>=0.5.0; extra == "docs"
Requires-Dist: griffe-pydantic>=1.1.7; extra == "docs"
Provides-Extra: all
Requires-Dist: napari>=0.4.15; extra == "all"
Dynamic: license-file
